e2ee/__init__.py
e2ee-0.0.4.dist-info/licenses/LICENSE
e2ee-0.0.4.dist-info/METADATA
e2ee-0.0.4.dist-info/WHEEL
e2ee-0.0.4.dist-info/top_level.txt
e2ee-0.0.4.dist-info/RECORD
