Metadata-Version: 2.4
Name: E2EE
Version: 0.0.4
Summary: End 2 End Encryption
Author-email: Santa <santa@hackers.gift>
License:                     GNU GENERAL PUBLIC LICENSE
Classifier: Programming Language :: Python :: 3
Classifier: License :: OSI Approved :: MIT License
Classifier: Operating System :: OS Independent
Requires-Python: >=3.9.10
License-File: LICENSE
Requires-Dist: cryptography==46.0.3
Provides-Extra: dev
Requires-Dist: pytest; extra == "dev"
Requires-Dist: cryptography; extra == "dev"
Dynamic: license-file
